network_latency_monitor/__init__.py
network_latency_monitor/cli.py
network_latency_monitor/config.py
network_latency_monitor/console_manager.py
network_latency_monitor/data_processing.py
network_latency_monitor/logger.py
network_latency_monitor/main.py
network_latency_monitor/ping_manager.py
network_latency_monitor/plot_generator.py
network_latency_monitor/utils.py
network_latency_monitor-0.2.2.dist-info/LICENSE
network_latency_monitor-0.2.2.dist-info/METADATA
network_latency_monitor-0.2.2.dist-info/WHEEL
network_latency_monitor-0.2.2.dist-info/entry_points.txt
network_latency_monitor-0.2.2.dist-info/RECORD
