Metadata-Version: 2.1
Name: network-latency-monitor
Version: 0.2.2
Summary: Monitor your network latency using real-time plots and cumulative plots
Home-page: https://github.com/m-usaid99/Network-Latency-Monitor
License: MIT
Keywords: network,latency,monitoring,ping
Author: Muhammad Usaid Rehman
Author-email: rehman.usaid@gmail.com
Requires-Python: >=3.10,<4.0
Classifier: License :: OSI Approved :: MIT License
Classifier: Operating System :: OS Independent
Classifier: Programming Language :: Python :: 3
Classifier: Programming Language :: Python :: 3.10
Classifier: Programming Language :: Python :: 3.11
Classifier: Programming Language :: Python :: 3.12
Requires-Dist: appdirs (>=1.4.4,<2.0.0)
Requires-Dist: asciichartpy (>=1.5.25,<2.0.0)
Requires-Dist: ipaddress (>=1.0.23,<2.0.0)
Requires-Dist: loguru (>=0.7.2,<0.8.0)
Requires-Dist: matplotlib (>=3.9.2,<4.0.0)
Requires-Dist: pandas (>=2.2.3,<3.0.0)
Requires-Dist: pytest (>=8.3.3,<9.0.0)
Requires-Dist: pyyaml (>=6.0.2,<7.0.0)
Requires-Dist: rich (>=13.9.2,<14.0.0)
Requires-Dist: seaborn (>=0.13.2,<0.14.0)
Project-URL: Documentation, https://network-latency-monitor.readthedocs.io/en/latest/
Project-URL: Repository, https://github.com/m-usaid99/Network-Latency-Monitor
